MANIFEST.in
README.md
deconf.py
setup.py
deconf.egg-info/PKG-INFO
deconf.egg-info/SOURCES.txt
deconf.egg-info/dependency_links.txt
deconf.egg-info/top_level.txt