Metadata-Version: 1.1
Name: deconf
Version: 0.1.1
Summary: An object system for building declarative configurations in Python.
Home-page: https://github.com/dustinlacewell/deconf
Author: Dustin Lacewell
Author-email: dlacewell@gmail.com
License: UNKNOWN
Platform: UNKNOWN
Provides: deconf
